{"nodes":[{"id":"push_specific_menu","label":"push_specific_menu.ts","file_type":"code","source_file":"C:\\Users\\H3X4N\\Documents\\GitHub\\Cuboic\\thambi_backend\\push_specific_menu.ts","source_location":"L1"},{"id":"push_specific_menu_updatespecificmenu","label":"updateSpecificMenu()","file_type":"code","source_file":"C:\\Users\\H3X4N\\Documents\\GitHub\\Cuboic\\thambi_backend\\push_specific_menu.ts","source_location":"L218"}],"edges":[{"source":"push_specific_menu","target":"client","relation":"imports_from","confidence":"EXTRACTED","source_file":"C:\\Users\\H3X4N\\Documents\\GitHub\\Cuboic\\thambi_backend\\push_specific_menu.ts","source_location":"L1","weight":1},{"source":"push_specific_menu","target":"dotenv","relation":"imports_from","confidence":"EXTRACTED","source_file":"C:\\Users\\H3X4N\\Documents\\GitHub\\Cuboic\\thambi_backend\\push_specific_menu.ts","source_location":"L2","weight":1},{"source":"push_specific_menu","target":"push_specific_menu_updatespecificmenu","relation":"contains","confidence":"EXTRACTED","source_file":"C:\\Users\\H3X4N\\Documents\\GitHub\\Cuboic\\thambi_backend\\push_specific_menu.ts","source_location":"L218","weight":1}]}