{"nodes":[{"id":"categories_controller","label":"categories.controller.ts","file_type":"code","source_file":"C:\\Users\\H3X4N\\Documents\\GitHub\\Cuboic\\thambi_backend\\src\\categories\\categories.controller.ts","source_location":"L1"},{"id":"categories_controller_categoriescontroller","label":"CategoriesController","file_type":"code","source_file":"C:\\Users\\H3X4N\\Documents\\GitHub\\Cuboic\\thambi_backend\\src\\categories\\categories.controller.ts","source_location":"L5"},{"id":"categories_controller_categoriescontroller_constructor","label":".constructor()","file_type":"code","source_file":"C:\\Users\\H3X4N\\Documents\\GitHub\\Cuboic\\thambi_backend\\src\\categories\\categories.controller.ts","source_location":"L6"},{"id":"categories_controller_categoriescontroller_findall","label":".findAll()","file_type":"code","source_file":"C:\\Users\\H3X4N\\Documents\\GitHub\\Cuboic\\thambi_backend\\src\\categories\\categories.controller.ts","source_location":"L9"}],"edges":[{"source":"categories_controller","target":"common","relation":"imports_from","confidence":"EXTRACTED","source_file":"C:\\Users\\H3X4N\\Documents\\GitHub\\Cuboic\\thambi_backend\\src\\categories\\categories.controller.ts","source_location":"L1","weight":1},{"source":"categories_controller","target":"categories_service","relation":"imports_from","confidence":"EXTRACTED","source_file":"C:\\Users\\H3X4N\\Documents\\GitHub\\Cuboic\\thambi_backend\\src\\categories\\categories.controller.ts","source_location":"L2","weight":1},{"source":"categories_controller","target":"categories_controller_categoriescontroller","relation":"contains","confidence":"EXTRACTED","source_file":"C:\\Users\\H3X4N\\Documents\\GitHub\\Cuboic\\thambi_backend\\src\\categories\\categories.controller.ts","source_location":"L5","weight":1},{"source":"categories_controller_categoriescontroller","target":"categories_controller_categoriescontroller_constructor","relation":"method","confidence":"EXTRACTED","source_file":"C:\\Users\\H3X4N\\Documents\\GitHub\\Cuboic\\thambi_backend\\src\\categories\\categories.controller.ts","source_location":"L6","weight":1},{"source":"categories_controller_categoriescontroller","target":"categories_controller_categoriescontroller_findall","relation":"method","confidence":"EXTRACTED","source_file":"C:\\Users\\H3X4N\\Documents\\GitHub\\Cuboic\\thambi_backend\\src\\categories\\categories.controller.ts","source_location":"L9","weight":1}]}