{"nodes":[{"id":"menu_controller","label":"menu.controller.ts","file_type":"code","source_file":"C:\\Users\\H3X4N\\Documents\\GitHub\\Cuboic\\thambi_backend\\src\\menu\\menu.controller.ts","source_location":"L1"},{"id":"menu_controller_menucontroller","label":"MenuController","file_type":"code","source_file":"C:\\Users\\H3X4N\\Documents\\GitHub\\Cuboic\\thambi_backend\\src\\menu\\menu.controller.ts","source_location":"L11"},{"id":"menu_controller_menucontroller_constructor","label":".constructor()","file_type":"code","source_file":"C:\\Users\\H3X4N\\Documents\\GitHub\\Cuboic\\thambi_backend\\src\\menu\\menu.controller.ts","source_location":"L12"},{"id":"menu_controller_menucontroller_getmenu","label":".getMenu()","file_type":"code","source_file":"C:\\Users\\H3X4N\\Documents\\GitHub\\Cuboic\\thambi_backend\\src\\menu\\menu.controller.ts","source_location":"L16"},{"id":"menu_controller_menucontroller_getadminmenu","label":".getAdminMenu()","file_type":"code","source_file":"C:\\Users\\H3X4N\\Documents\\GitHub\\Cuboic\\thambi_backend\\src\\menu\\menu.controller.ts","source_location":"L24"},{"id":"menu_controller_menucontroller_createitem","label":".createItem()","file_type":"code","source_file":"C:\\Users\\H3X4N\\Documents\\GitHub\\Cuboic\\thambi_backend\\src\\menu\\menu.controller.ts","source_location":"L32"},{"id":"menu_controller_menucontroller_updateitem","label":".updateItem()","file_type":"code","source_file":"C:\\Users\\H3X4N\\Documents\\GitHub\\Cuboic\\thambi_backend\\src\\menu\\menu.controller.ts","source_location":"L40"},{"id":"menu_controller_menucontroller_bulkupdate","label":".bulkUpdate()","file_type":"code","source_file":"C:\\Users\\H3X4N\\Documents\\GitHub\\Cuboic\\thambi_backend\\src\\menu\\menu.controller.ts","source_location":"L47"}],"edges":[{"source":"menu_controller","target":"common","relation":"imports_from","confidence":"EXTRACTED","source_file":"C:\\Users\\H3X4N\\Documents\\GitHub\\Cuboic\\thambi_backend\\src\\menu\\menu.controller.ts","source_location":"L1","weight":1},{"source":"menu_controller","target":"menu_service","relation":"imports_from","confidence":"EXTRACTED","source_file":"C:\\Users\\H3X4N\\Documents\\GitHub\\Cuboic\\thambi_backend\\src\\menu\\menu.controller.ts","source_location":"L2","weight":1},{"source":"menu_controller","target":"query_menu_dto","relation":"imports_from","confidence":"EXTRACTED","source_file":"C:\\Users\\H3X4N\\Documents\\GitHub\\Cuboic\\thambi_backend\\src\\menu\\menu.controller.ts","source_location":"L3","weight":1},{"source":"menu_controller","target":"create_menu_item_dto","relation":"imports_from","confidence":"EXTRACTED","source_file":"C:\\Users\\H3X4N\\Documents\\GitHub\\Cuboic\\thambi_backend\\src\\menu\\menu.controller.ts","source_location":"L4","weight":1},{"source":"menu_controller","target":"update_menu_item_dto","relation":"imports_from","confidence":"EXTRACTED","source_file":"C:\\Users\\H3X4N\\Documents\\GitHub\\Cuboic\\thambi_backend\\src\\menu\\menu.controller.ts","source_location":"L5","weight":1},{"source":"menu_controller","target":"jwt_auth_guard","relation":"imports_from","confidence":"EXTRACTED","source_file":"C:\\Users\\H3X4N\\Documents\\GitHub\\Cuboic\\thambi_backend\\src\\menu\\menu.controller.ts","source_location":"L6","weight":1},{"source":"menu_controller","target":"roles_guard","relation":"imports_from","confidence":"EXTRACTED","source_file":"C:\\Users\\H3X4N\\Documents\\GitHub\\Cuboic\\thambi_backend\\src\\menu\\menu.controller.ts","source_location":"L7","weight":1},{"source":"menu_controller","target":"roles_decorator","relation":"imports_from","confidence":"EXTRACTED","source_file":"C:\\Users\\H3X4N\\Documents\\GitHub\\Cuboic\\thambi_backend\\src\\menu\\menu.controller.ts","source_location":"L8","weight":1},{"source":"menu_controller","target":"menu_controller_menucontroller","relation":"contains","confidence":"EXTRACTED","source_file":"C:\\Users\\H3X4N\\Documents\\GitHub\\Cuboic\\thambi_backend\\src\\menu\\menu.controller.ts","source_location":"L11","weight":1},{"source":"menu_controller_menucontroller","target":"menu_controller_menucontroller_constructor","relation":"method","confidence":"EXTRACTED","source_file":"C:\\Users\\H3X4N\\Documents\\GitHub\\Cuboic\\thambi_backend\\src\\menu\\menu.controller.ts","source_location":"L12","weight":1},{"source":"menu_controller_menucontroller","target":"menu_controller_menucontroller_getmenu","relation":"method","confidence":"EXTRACTED","source_file":"C:\\Users\\H3X4N\\Documents\\GitHub\\Cuboic\\thambi_backend\\src\\menu\\menu.controller.ts","source_location":"L16","weight":1},{"source":"menu_controller_menucontroller","target":"menu_controller_menucontroller_getadminmenu","relation":"method","confidence":"EXTRACTED","source_file":"C:\\Users\\H3X4N\\Documents\\GitHub\\Cuboic\\thambi_backend\\src\\menu\\menu.controller.ts","source_location":"L24","weight":1},{"source":"menu_controller_menucontroller","target":"menu_controller_menucontroller_createitem","relation":"method","confidence":"EXTRACTED","source_file":"C:\\Users\\H3X4N\\Documents\\GitHub\\Cuboic\\thambi_backend\\src\\menu\\menu.controller.ts","source_location":"L32","weight":1},{"source":"menu_controller_menucontroller","target":"menu_controller_menucontroller_updateitem","relation":"method","confidence":"EXTRACTED","source_file":"C:\\Users\\H3X4N\\Documents\\GitHub\\Cuboic\\thambi_backend\\src\\menu\\menu.controller.ts","source_location":"L40","weight":1},{"source":"menu_controller_menucontroller","target":"menu_controller_menucontroller_bulkupdate","relation":"method","confidence":"EXTRACTED","source_file":"C:\\Users\\H3X4N\\Documents\\GitHub\\Cuboic\\thambi_backend\\src\\menu\\menu.controller.ts","source_location":"L47","weight":1}]}