{"nodes":[{"id":"main","label":"main.ts","file_type":"code","source_file":"C:\\Users\\H3X4N\\Documents\\GitHub\\Cuboic\\thambi_desktop\\electron\\main.ts","source_location":"L1"},{"id":"main_createwindow","label":"createWindow()","file_type":"code","source_file":"C:\\Users\\H3X4N\\Documents\\GitHub\\Cuboic\\thambi_desktop\\electron\\main.ts","source_location":"L27"}],"edges":[{"source":"main","target":"electron","relation":"imports_from","confidence":"EXTRACTED","source_file":"C:\\Users\\H3X4N\\Documents\\GitHub\\Cuboic\\thambi_desktop\\electron\\main.ts","source_location":"L1","weight":1},{"source":"main","target":"node_path","relation":"imports_from","confidence":"EXTRACTED","source_file":"C:\\Users\\H3X4N\\Documents\\GitHub\\Cuboic\\thambi_desktop\\electron\\main.ts","source_location":"L2","weight":1},{"source":"main","target":"node_fs","relation":"imports_from","confidence":"EXTRACTED","source_file":"C:\\Users\\H3X4N\\Documents\\GitHub\\Cuboic\\thambi_desktop\\electron\\main.ts","source_location":"L3","weight":1},{"source":"main","target":"electron_pos_printer","relation":"imports_from","confidence":"EXTRACTED","source_file":"C:\\Users\\H3X4N\\Documents\\GitHub\\Cuboic\\thambi_desktop\\electron\\main.ts","source_location":"L4","weight":1},{"source":"main","target":"main_createwindow","relation":"contains","confidence":"EXTRACTED","source_file":"C:\\Users\\H3X4N\\Documents\\GitHub\\Cuboic\\thambi_desktop\\electron\\main.ts","source_location":"L27","weight":1}]}