{"nodes":[{"id":"ui_dialog","label":"dialog.tsx","file_type":"code","source_file":"C:\\Users\\H3X4N\\Documents\\GitHub\\Cuboic\\onomex_public\\src\\app\\components\\ui\\dialog.tsx","source_location":"L1"},{"id":"ui_dialog_dialogoverlay","label":"DialogOverlay()","file_type":"code","source_file":"C:\\Users\\H3X4N\\Documents\\GitHub\\Cuboic\\onomex_public\\src\\app\\components\\ui\\dialog.tsx","source_location":"L33"},{"id":"ui_dialog_cn","label":"cn()","file_type":"code","source_file":"C:\\Users\\H3X4N\\Documents\\GitHub\\Cuboic\\onomex_public\\src\\app\\components\\ui\\dialog.tsx","source_location":"L79"},{"id":"ui_dialog_dialogdescription","label":"DialogDescription()","file_type":"code","source_file":"C:\\Users\\H3X4N\\Documents\\GitHub\\Cuboic\\onomex_public\\src\\app\\components\\ui\\dialog.tsx","source_location":"L111"}],"edges":[{"source":"ui_dialog","target":"react","relation":"imports_from","confidence":"EXTRACTED","source_file":"C:\\Users\\H3X4N\\Documents\\GitHub\\Cuboic\\onomex_public\\src\\app\\components\\ui\\dialog.tsx","source_location":"L3","weight":1},{"source":"ui_dialog","target":"react_dialog","relation":"imports_from","confidence":"EXTRACTED","source_file":"C:\\Users\\H3X4N\\Documents\\GitHub\\Cuboic\\onomex_public\\src\\app\\components\\ui\\dialog.tsx","source_location":"L4","weight":1},{"source":"ui_dialog","target":"lucide_react","relation":"imports_from","confidence":"EXTRACTED","source_file":"C:\\Users\\H3X4N\\Documents\\GitHub\\Cuboic\\onomex_public\\src\\app\\components\\ui\\dialog.tsx","source_location":"L5","weight":1},{"source":"ui_dialog","target":"c_users_h3x4n_documents_github_cuboic_onomex_public_src_app_components_ui_utils_ts","relation":"imports_from","confidence":"EXTRACTED","source_file":"C:\\Users\\H3X4N\\Documents\\GitHub\\Cuboic\\onomex_public\\src\\app\\components\\ui\\dialog.tsx","source_location":"L7","weight":1},{"source":"ui_dialog","target":"ui_dialog_dialogoverlay","relation":"contains","confidence":"EXTRACTED","source_file":"C:\\Users\\H3X4N\\Documents\\GitHub\\Cuboic\\onomex_public\\src\\app\\components\\ui\\dialog.tsx","source_location":"L33","weight":1},{"source":"ui_dialog","target":"ui_dialog_cn","relation":"contains","confidence":"EXTRACTED","source_file":"C:\\Users\\H3X4N\\Documents\\GitHub\\Cuboic\\onomex_public\\src\\app\\components\\ui\\dialog.tsx","source_location":"L79","weight":1},{"source":"ui_dialog","target":"ui_dialog_cn","relation":"contains","confidence":"EXTRACTED","source_file":"C:\\Users\\H3X4N\\Documents\\GitHub\\Cuboic\\onomex_public\\src\\app\\components\\ui\\dialog.tsx","source_location":"L89","weight":1},{"source":"ui_dialog","target":"ui_dialog_dialogdescription","relation":"contains","confidence":"EXTRACTED","source_file":"C:\\Users\\H3X4N\\Documents\\GitHub\\Cuboic\\onomex_public\\src\\app\\components\\ui\\dialog.tsx","source_location":"L111","weight":1}]}