{"nodes":[{"id":"staff_kitchenscreen","label":"KitchenScreen.tsx","file_type":"code","source_file":"C:\\Users\\H3X4N\\Documents\\GitHub\\Cuboic\\onomex_mobile\\src\\screens\\staff\\KitchenScreen.tsx","source_location":"L1"},{"id":"staff_kitchenscreen_gettablenum","label":"getTableNum()","file_type":"code","source_file":"C:\\Users\\H3X4N\\Documents\\GitHub\\Cuboic\\onomex_mobile\\src\\screens\\staff\\KitchenScreen.tsx","source_location":"L15"},{"id":"staff_kitchenscreen_handleadvanceorder","label":"handleAdvanceOrder()","file_type":"code","source_file":"C:\\Users\\H3X4N\\Documents\\GitHub\\Cuboic\\onomex_mobile\\src\\screens\\staff\\KitchenScreen.tsx","source_location":"L148"},{"id":"staff_kitchenscreen_handlelogout","label":"handleLogout()","file_type":"code","source_file":"C:\\Users\\H3X4N\\Documents\\GitHub\\Cuboic\\onomex_mobile\\src\\screens\\staff\\KitchenScreen.tsx","source_location":"L160"}],"edges":[{"source":"staff_kitchenscreen","target":"react","relation":"imports_from","confidence":"EXTRACTED","source_file":"C:\\Users\\H3X4N\\Documents\\GitHub\\Cuboic\\onomex_mobile\\src\\screens\\staff\\KitchenScreen.tsx","source_location":"L1","weight":1},{"source":"staff_kitchenscreen","target":"react_native","relation":"imports_from","confidence":"EXTRACTED","source_file":"C:\\Users\\H3X4N\\Documents\\GitHub\\Cuboic\\onomex_mobile\\src\\screens\\staff\\KitchenScreen.tsx","source_location":"L2","weight":1},{"source":"staff_kitchenscreen","target":"vector_icons","relation":"imports_from","confidence":"EXTRACTED","source_file":"C:\\Users\\H3X4N\\Documents\\GitHub\\Cuboic\\onomex_mobile\\src\\screens\\staff\\KitchenScreen.tsx","source_location":"L6","weight":1},{"source":"staff_kitchenscreen","target":"c_users_h3x4n_documents_github_cuboic_onomex_mobile_src_api_orders_ts","relation":"imports_from","confidence":"EXTRACTED","source_file":"C:\\Users\\H3X4N\\Documents\\GitHub\\Cuboic\\onomex_mobile\\src\\screens\\staff\\KitchenScreen.tsx","source_location":"L7","weight":1},{"source":"staff_kitchenscreen","target":"c_users_h3x4n_documents_github_cuboic_onomex_mobile_src_context_authcontext_tsx","relation":"imports_from","confidence":"EXTRACTED","source_file":"C:\\Users\\H3X4N\\Documents\\GitHub\\Cuboic\\onomex_mobile\\src\\screens\\staff\\KitchenScreen.tsx","source_location":"L8","weight":1},{"source":"staff_kitchenscreen","target":"c_users_h3x4n_documents_github_cuboic_onomex_mobile_src_context_themecontext_tsx","relation":"imports_from","confidence":"EXTRACTED","source_file":"C:\\Users\\H3X4N\\Documents\\GitHub\\Cuboic\\onomex_mobile\\src\\screens\\staff\\KitchenScreen.tsx","source_location":"L9","weight":1},{"source":"staff_kitchenscreen","target":"c_users_h3x4n_documents_github_cuboic_onomex_mobile_src_context_socketcontext_tsx","relation":"imports_from","confidence":"EXTRACTED","source_file":"C:\\Users\\H3X4N\\Documents\\GitHub\\Cuboic\\onomex_mobile\\src\\screens\\staff\\KitchenScreen.tsx","source_location":"L10","weight":1},{"source":"staff_kitchenscreen","target":"react_native_safe_area_context","relation":"imports_from","confidence":"EXTRACTED","source_file":"C:\\Users\\H3X4N\\Documents\\GitHub\\Cuboic\\onomex_mobile\\src\\screens\\staff\\KitchenScreen.tsx","source_location":"L11","weight":1},{"source":"staff_kitchenscreen","target":"c_users_h3x4n_documents_github_cuboic_onomex_mobile_src_theme_ts","relation":"imports_from","confidence":"EXTRACTED","source_file":"C:\\Users\\H3X4N\\Documents\\GitHub\\Cuboic\\onomex_mobile\\src\\screens\\staff\\KitchenScreen.tsx","source_location":"L12","weight":1},{"source":"staff_kitchenscreen","target":"c_users_h3x4n_documents_github_cuboic_onomex_mobile_src_hooks_useoptimisticmutation_ts","relation":"imports_from","confidence":"EXTRACTED","source_file":"C:\\Users\\H3X4N\\Documents\\GitHub\\Cuboic\\onomex_mobile\\src\\screens\\staff\\KitchenScreen.tsx","source_location":"L13","weight":1},{"source":"staff_kitchenscreen","target":"staff_kitchenscreen_gettablenum","relation":"contains","confidence":"EXTRACTED","source_file":"C:\\Users\\H3X4N\\Documents\\GitHub\\Cuboic\\onomex_mobile\\src\\screens\\staff\\KitchenScreen.tsx","source_location":"L15","weight":1},{"source":"staff_kitchenscreen","target":"staff_kitchenscreen_handleadvanceorder","relation":"contains","confidence":"EXTRACTED","source_file":"C:\\Users\\H3X4N\\Documents\\GitHub\\Cuboic\\onomex_mobile\\src\\screens\\staff\\KitchenScreen.tsx","source_location":"L148","weight":1},{"source":"staff_kitchenscreen","target":"staff_kitchenscreen_handlelogout","relation":"contains","confidence":"EXTRACTED","source_file":"C:\\Users\\H3X4N\\Documents\\GitHub\\Cuboic\\onomex_mobile\\src\\screens\\staff\\KitchenScreen.tsx","source_location":"L160","weight":1}]}