{
  "schemaVersion": 1,
  "worktreePath": "C:\\Users\\H3X4N\\Documents\\GitHub\\Cuboic",
  "gitDir": "C:\\Users\\H3X4N\\Documents\\GitHub\\Cuboic\\.git",
  "commonGitDir": "C:\\Users\\H3X4N\\Documents\\GitHub\\Cuboic\\.git",
  "firstSeenHead": "bf123b9af584db8e112a6d9bf9e2daeba6ceb383",
  "lastSeenHead": "461ba3095daab40db977029c0a8b9da2cbf1fd29",
  "lastAnalyzedHead": "461ba3095daab40db977029c0a8b9da2cbf1fd29",
  "createdAt": "2026-05-22T17:26:05.444Z",
  "updatedAt": "2026-05-27T05:50:06.909Z"
}
