{
  "schemaVersion": 1,
  "worktreePath": "C:\\Users\\H3X4N\\Documents\\GitHub\\Cuboic",
  "gitDir": "C:\\Users\\H3X4N\\Documents\\GitHub\\Cuboic\\.git",
  "commonGitDir": "C:\\Users\\H3X4N\\Documents\\GitHub\\Cuboic\\.git",
  "firstSeenHead": "bf123b9af584db8e112a6d9bf9e2daeba6ceb383",
  "lastSeenHead": "100ab38446a5d1c3e4764e95b2a20c02151f98b8",
  "lastAnalyzedHead": "100ab38446a5d1c3e4764e95b2a20c02151f98b8",
  "createdAt": "2026-05-22T17:26:05.444Z",
  "updatedAt": "2026-05-27T08:57:14.905Z"
}
